[
  {
    "id": "9c96328b46963eb890e1b0cf7084f9fa",
    "distribution": "kona",
    "version": {
      "components": [
        8,
        0,
        462
      ],
      "build": null,
      "pre_release": null
    },
    "distribution_version": {
      "components": [
        8,
        0,
        462
      ],
      "build": null,
      "pre_release": null
    },
    "architecture": "aarch64",
    "operating_system": "linux",
    "package_type": "jdk",
    "archive_type": "targz",
    "download_url": "https://github.com/Tencent/TencentKona-8/releases/download/8.0.23-GA/TencentKona8.0.23.b1_jdk_linux-musl-aarch64_8u462.tar.gz",
    "checksum": null,
    "checksum_type": "md5",
    "size": 104235730,
    "lib_c_type": "musl",
    "javafx_bundled": false,
    "term_of_support": "lts",
    "release_status": "ga",
    "latest_build_available": true
  },
  {
    "id": "dbf856e85e930fee87661c9a6c5d96c3",
    "distribution": "kona",
    "version": {
      "components": [
        8,
        0,
        452
      ],
      "build": null,
      "pre_release": null
    },
    "distribution_version": {
      "components": [
        8,
        0,
        452
      ],
      "build": null,
      "pre_release": null
    },
    "architecture": "aarch64",
    "operating_system": "linux",
    "package_type": "jdk",
    "archive_type": "targz",
    "download_url": "https://github.com/Tencent/TencentKona-8/releases/download/8.0.22-GA/TencentKona8.0.22.b1_jdk_linux-musl-aarch64_8u452.tar.gz",
    "checksum": null,
    "checksum_type": "md5",
    "size": 104227057,
    "lib_c_type": "musl",
    "javafx_bundled": false,
    "term_of_support": "lts",
    "release_status": "ga",
    "latest_build_available": false
  },
  {
    "id": "589a6262662b65cf84fd892aa34a0e71",
    "distribution": "kona",
    "version": {
      "components": [
        8,
        0,
        442
      ],
      "build": null,
      "pre_release": null
    },
    "distribution_version": {
      "components": [
        8,
        0,
        442
      ],
      "build": null,
      "pre_release": null
    },
    "architecture": "aarch64",
    "operating_system": "linux",
    "package_type": "jdk",
    "archive_type": "targz",
    "download_url": "https://github.com/Tencent/TencentKona-8/releases/download/8.0.21-GA/TencentKona8.0.21.b1_jdk_linux-musl-aarch64_8u442.tar.gz",
    "checksum": null,
    "checksum_type": "md5",
    "size": 104215780,
    "lib_c_type": "musl",
    "javafx_bundled": false,
    "term_of_support": "lts",
    "release_status": "ga",
    "latest_build_available": false
  },
  {
    "id": "975fe021848ab3d768e142eeba8ecc17",
    "distribution": "kona",
    "version": {
      "components": [
        8,
        0,
        432
      ],
      "build": null,
      "pre_release": null
    },
    "distribution_version": {
      "components": [
        8,
        0,
        432
      ],
      "build": null,
      "pre_release": null
    },
    "architecture": "aarch64",
    "operating_system": "linux",
    "package_type": "jdk",
    "archive_type": "targz",
    "download_url": "https://github.com/Tencent/TencentKona-8/releases/download/8.0.20-GA/TencentKona8.0.20.b1_jdk_linux-musl-aarch64_8u432.tar.gz",
    "checksum": null,
    "checksum_type": "md5",
    "size": 104189892,
    "lib_c_type": "musl",
    "javafx_bundled": false,
    "term_of_support": "lts",
    "release_status": "ga",
    "latest_build_available": false
  },
  {
    "id": "65db1217a0bf925839f6252e55aedb91",
    "distribution": "kona",
    "version": {
      "components": [
        8,
        0,
        422
      ],
      "build": null,
      "pre_release": null
    },
    "distribution_version": {
      "components": [
        8,
        0,
        422
      ],
      "build": null,
      "pre_release": null
    },
    "architecture": "aarch64",
    "operating_system": "linux",
    "package_type": "jdk",
    "archive_type": "targz",
    "download_url": "https://github.com/Tencent/TencentKona-8/releases/download/8.0.19-GA/TencentKona8.0.19.b1_jdk_linux-musl-aarch64_8u422.tar.gz",
    "checksum": null,
    "checksum_type": "md5",
    "size": 104162517,
    "lib_c_type": "musl",
    "javafx_bundled": false,
    "term_of_support": "lts",
    "release_status": "ga",
    "latest_build_available": false
  },
  {
    "id": "37746a86e7069974a8e0694ae57c68b7",
    "distribution": "kona",
    "version": {
      "components": [
        8,
        0,
        412
      ],
      "build": null,
      "pre_release": null
    },
    "distribution_version": {
      "components": [
        8,
        0,
        412
      ],
      "build": null,
      "pre_release": null
    },
    "architecture": "aarch64",
    "operating_system": "linux",
    "package_type": "jdk",
    "archive_type": "targz",
    "download_url": "https://github.com/Tencent/TencentKona-8/releases/download/8.0.18-GA/TencentKona8.0.18.b1_jdk_linux-musl-aarch64_8u412.tar.gz",
    "checksum": null,
    "checksum_type": "md5",
    "size": 104155609,
    "lib_c_type": "musl",
    "javafx_bundled": false,
    "term_of_support": "lts",
    "release_status": "ga",
    "latest_build_available": false
  },
  {
    "id": "c888b9016129d98f002ef4f19d7ca4d7",
    "distribution": "kona",
    "version": {
      "components": [
        8,
        0,
        402
      ],
      "build": null,
      "pre_release": null
    },
    "distribution_version": {
      "components": [
        8,
        0,
        402
      ],
      "build": null,
      "pre_release": null
    },
    "architecture": "aarch64",
    "operating_system": "linux",
    "package_type": "jdk",
    "archive_type": "targz",
    "download_url": "https://github.com/Tencent/TencentKona-8/releases/download/8.0.17-GA/TencentKona8.0.17.b1_jdk_linux-musl-aarch64_8u402.tar.gz",
    "checksum": null,
    "checksum_type": "md5",
    "size": 104051218,
    "lib_c_type": "musl",
    "javafx_bundled": false,
    "term_of_support": "lts",
    "release_status": "ga",
    "latest_build_available": false
  },
  {
    "id": "eefc8170da2d2cc6414cb1d09255d956",
    "distribution": "kona",
    "version": {
      "components": [
        8,
        0,
        392
      ],
      "build": null,
      "pre_release": null
    },
    "distribution_version": {
      "components": [
        8,
        0,
        392
      ],
      "build": null,
      "pre_release": null
    },
    "architecture": "aarch64",
    "operating_system": "linux",
    "package_type": "jdk",
    "archive_type": "targz",
    "download_url": "https://github.com/Tencent/TencentKona-8/releases/download/8.0.16-GA/TencentKona8.0.16.b1_jdk_linux-musl-aarch64_8u392.tar.gz",
    "checksum": null,
    "checksum_type": "md5",
    "size": 103931001,
    "lib_c_type": "musl",
    "javafx_bundled": false,
    "term_of_support": "lts",
    "release_status": "ga",
    "latest_build_available": false
  },
  {
    "id": "bc083ea3a0316bfa5ad7c1d046e646b0",
    "distribution": "kona",
    "version": {
      "components": [
        8,
        0,
        382
      ],
      "build": null,
      "pre_release": null
    },
    "distribution_version": {
      "components": [
        8,
        0,
        382
      ],
      "build": null,
      "pre_release": null
    },
    "architecture": "aarch64",
    "operating_system": "linux",
    "package_type": "jdk",
    "archive_type": "targz",
    "download_url": "https://github.com/Tencent/TencentKona-8/releases/download/8.0.15-GA/TencentKona8.0.15.b1_jdk_linux-musl-aarch64_8u382.tar.gz",
    "checksum": null,
    "checksum_type": "md5",
    "size": 103914650,
    "lib_c_type": "musl",
    "javafx_bundled": false,
    "term_of_support": "lts",
    "release_status": "ga",
    "latest_build_available": false
  },
  {
    "id": "682be5297aedd7a7f2f4f8efb118ccff",
    "distribution": "kona",
    "version": {
      "components": [
        8,
        0,
        372
      ],
      "build": null,
      "pre_release": null
    },
    "distribution_version": {
      "components": [
        8,
        0,
        372
      ],
      "build": null,
      "pre_release": null
    },
    "architecture": "aarch64",
    "operating_system": "linux",
    "package_type": "jdk",
    "archive_type": "targz",
    "download_url": "https://github.com/Tencent/TencentKona-8/releases/download/8.0.14-GA/TencentKona8.0.14.b1_jdk_linux-musl-aarch64_8u372.tar.gz",
    "checksum": null,
    "checksum_type": "md5",
    "size": 103885779,
    "lib_c_type": "musl",
    "javafx_bundled": false,
    "term_of_support": "lts",
    "release_status": "ga",
    "latest_build_available": false
  }
]